LICENCE.txt
MANIFEST.in
README.md
setup.py
cgr_pdfextract.egg-info/PKG-INFO
cgr_pdfextract.egg-info/SOURCES.txt
cgr_pdfextract.egg-info/dependency_links.txt
cgr_pdfextract.egg-info/top_level.txt
cgrextract/__init__.py