Metadata-Version: 2.1
Name: cgr-pdfextract
Version: 3.0.10
Summary: Herramienta para la extracción de datos de los "Informes de Control Posterior" de la Contraloria General de la República" del Perú
Home-page: https://github.com/JelsinPalomino/cgr-pdfextract
Author: Jelsin Palomino
Author-email: jstpalomino@hotmail.com
License: MIT
Keywords: Perú,Peru,contraloria,informes de control posterior
Platform: UNKNOWN
Classifier: Intended Audience :: Education
Classifier: Operating System :: Microsoft :: Windows :: Windows 10
Classifier: Programming Language :: Python :: 3
